physer/__init__.py
physer/collider.py
physer/collision.py
physer/world.py
physer-1.0.0.dist-info/licenses/LICENSE
physer-1.0.0.dist-info/METADATA
physer-1.0.0.dist-info/WHEEL
physer-1.0.0.dist-info/top_level.txt
physer-1.0.0.dist-info/RECORD
